purplekoala-0.4.0.dist-info/METADATA
purplekoala-0.4.0.dist-info/WHEEL
purplekoala/__init__.py
purplekoala/_core.abi3.so
purplekoala/_core.pyi
purplekoala/differential/__init__.py
purplekoala/differential/discrete.py
purplekoala/distributions/__init__.py
purplekoala/distributions/cvdistributions.py
purplekoala/matrix/__init__.py
purplekoala/matrix/elementary.py
purplekoala/model/__init__.py
purplekoala/model/regression.py
purplekoala/py.typed
purplekoala-0.4.0.dist-info/RECORD
