Metadata-Version: 2.4
Name: purplekoala
Version: 0.4.0
Requires-Dist: ipykernel>=6.30.1
Requires-Dist: jupyter>=1.1.1
Requires-Dist: matplotlib>=3.10.6
Requires-Dist: numpy>=2.3.3
Requires-Dist: pandas>=2.3.2
Requires-Dist: polars>=1.34.0
Requires-Dist: seaborn>=0.13.2
Requires-Dist: statsmodels>=0.14.5
Requires-Dist: torch>=2.8.0
Requires-Dist: twine>=6.1.0
Summary: Add your description here
Author-email: purplekoalagh <purplekoala586@gmail.com>
Requires-Python: >=3.12
